iduate_bank_card/BankCard.py
iduate_bank_card/__init__.py
iduate_bank_card-4.1.dist-info/DESCRIPTION.rst
iduate_bank_card-4.1.dist-info/METADATA
iduate_bank_card-4.1.dist-info/RECORD
iduate_bank_card-4.1.dist-info/WHEEL
iduate_bank_card-4.1.dist-info/metadata.json
iduate_bank_card-4.1.dist-info/top_level.txt
