Metadata-Version: 2.0
Name: iduate-bank-card
Version: 4.1
Summary: Bank Card - Luhn Algorithm
Home-page: UNKNOWN
Author: UNKNOWN
Author-email: UNKNOWN
License: UNKNOWN
Platform: UNKNOWN
